flask_fontpicker/__init__.py
flask_fontpicker-0.3.dist-info/METADATA
flask_fontpicker-0.3.dist-info/WHEEL
flask_fontpicker-0.3.dist-info/top_level.txt
flask_fontpicker-0.3.dist-info/RECORD
