Metadata-Version: 2.4
Name: Flask-Fontpicker
Version: 0.3
Summary: web font picker flask extension
Home-page: https://github.com/mrf345/flask_fontpicker/
Download-URL: https://github.com/mrf345/flask_fontpicker/archive/0.3.tar.gz
Author: Mohamed Feddad
Author-email: mrf345@gmail.com
License: MIT
Keywords: flask,extension,web,google,font,picker,Jquery-UI,fontpicker
Platform: any
Classifier: Environment :: Web Environment
Classifier: Intended Audience :: Developers
Classifier: License :: OSI Approved :: MIT License
Classifier: Operating System :: OS Independent
Classifier: Programming Language :: Python
Classifier: Topic :: Internet :: WWW/HTTP :: Dynamic Content
Classifier: Topic :: Software Development :: Libraries :: Python Modules
Requires-Dist: Flask
Requires-Dist: Flask-Bootstrap
Requires-Dist: MarkupSafe
Dynamic: author
Dynamic: author-email
Dynamic: classifier
Dynamic: description
Dynamic: description-content-type
Dynamic: download-url
Dynamic: home-page
Dynamic: keywords
Dynamic: license
Dynamic: platform
Dynamic: requires-dist
Dynamic: summary
